Gene_Network/cycle.v
`timescale 1ns/100ps
module cycle (clk, init_val_chk, x, cycle_chk);
	input wire clk;
	input wire init_val_chk;
	input wire [7:0] x;
	output reg cycle_chk;
	reg [7:0] state_1;
	reg [7:0] state_2;

	always @(init_val_chk) begin
		flag = 0;
		state_1 = 8'b0000_0000;
		state_2 = 8'b0000_0000;
	end

	always @(posedge clk) begin
		if (state_2 == x)
			flag = 1;
		else
			flag = 0;
		state_2 = state_1;
		state_1 = x;
	end
endmodule

Gene_Network/fixed_point_checker.v
`timescale 1ns/100ps
module fixed_point_cheker(clk, rst, x, flag);
	input wire clk;						//clock signal
	input wire [7:0] rst;		//is init val changed?
	input wire [7:0] x;					//current gene state
	output reg flag;					//Fixed point has been FOUND!
	reg [7:0] state;					//state of x[t]

	always @(rst) begin		//if init val changed
		flag = 0;						//reset cycle  flag
	end

	always @(posedge clk) begin		//synchronized with positive edge clock signal
		if (state == x)				//when x[t-1] == x[t+1]
			flag = 1;					//FIXED POINT!!!	
		else
			flag = 0;
		state = x;					//save x[t]
	end
endmodule

Gene_Network/gene_net.v
`timescale 1ns/100ps

module gene_net(clk, x_in, x_out);
	input wire clk;
	input wire [7:0] x_in;
	output reg [7:0] x_out;
	reg [7:0] state;
	
	always @(x_in) begin
		state <= x_in;
	end

	always @(posedge clk)
	begin
		x_out[0] <= ~state[2] & state[6] & ~state[7];
		x_out[1] <= (state[4] | state[5]) & ~state[7];
		x_out[2] <= state[7];
		x_out[3] <= state[1] & ~state[6];
		x_out[4] <= state[1] | state[3];
		x_out[5] <= state[2] & ~state[7];
		x_out[6] <= state[1] & ~state[7];
		x_out[7] <= ~(state[0] | state[1]) & (state[3] | state[6]);
		state = x_out;
	end

	always @(x_in) begin
		state <= x_in;
	end

endmodule

Gene_Network/testbench.v
`timescale 1ns/100ps
`include "gene_net.v"
`include "fixed_point_checker.v"
`include "cycle.v"

module tb_top;
endmodule


module tb_gene_net;
	reg clk;
	reg [7:0] init_val;
	wire [7:0] x_out;

	//clk signal generation
	initial begin
		clk = 0;
		forever #1 clk = ~clk;
	end

	//file dumping
	initial begin
		$dumpfile("wave.vcd");
		$dumpvars(0, tb_gene_net);
	end

	//input signal generation
	initial begin
		init_val = 8'b0000_0000;	//0 	fixed_point	0000_0000
		#20
		init_val = 8'b0011_1000;	//56 	cycle		0001_1100
		#20
		init_val = 8'b0110_0011;	//99 	fixed_point	0101_0011
		#20
		init_val = 8'b0111_1100;	//124 	cycle		1011_0010
		#20
		init_val = 8'b1111_1111;	//255 	fixed_point	0101_0011
		#20
		$finish;					//end simulation
	end

	//instansiation gene_net
	gene_net G1 (.clk(clk), .x_in(init_val), .x_out(x_out));


endmodule



module tb_fixed_point_chk;
//
endmodule

module tb_cycle;
//
endmodule

Gene_Network/wave.vcd
$date
	Sat May 27 15:38:40 2023
$end
$version
	ModelSim Version 2020.1
$end
$timescale
	100ps
$end

$scope module tb_gene_net $end
$var reg 1 ! clk $end
$var reg 8 " init_val [7:0] $end
$var wire 1 # x_out [7] $end
$var wire 1 $ x_out [6] $end
$var wire 1 % x_out [5] $end
$var wire 1 & x_out [4] $end
$var wire 1 ' x_out [3] $end
$var wire 1 ( x_out [2] $end
$var wire 1 ) x_out [1] $end
$var wire 1 * x_out [0] $end

$scope module G1 $end
$var wire 1 + clk $end
$var wire 1 , x_in [7] $end
$var wire 1 - x_in [6] $end
$var wire 1 . x_in [5] $end
$var wire 1 / x_in [4] $end
$var wire 1 0 x_in [3] $end
$var wire 1 1 x_in [2] $end
$var wire 1 2 x_in [1] $end
$var wire 1 3 x_in [0] $end
$var reg 8 4 x_out [7:0] $end
$var reg 8 5 state [7:0] $end
$upscope $end
$upscope $end
$enddefinitions $end
#0
$dumpvars
0!
b0 "
bx 4
b0 5
x*
x)
x(
x'
x&
x%
x$
x#
03
02
01
00
0/
0.
0-
0,
0+
$end
#10
1!
1+
bx 5
bx0 4
bx00 4
bx000 4
bx0000 4
bx00000 4
bx000000 4
bx0000000 4
b0 4
0*
0)
0(
0'
0&
0%
0$
0#
#20
0!
0+
#30
1!
1+
b0 5
b0x 4
b0xx 4
b0xxx 4
b0xxxx 4
b0xxxxx 4
b0xxxxxx 4
b0xxxxxxx 4
bx 4
x*
x)
x(
x'
x&
x%
x$
x#
#40
0!
0+
#50
1!
1+
bx 5
bx0 4
bx00 4
bx000 4
bx0000 4
bx00000 4
bx000000 4
bx0000000 4
b0 4
0*
0)
0(
0'
0&
0%
0$
0#
#60
0!
0+
#70
1!
1+
b0 5
b0x 4
b0xx 4
b0xxx 4
b0xxxx 4
b0xxxxx 4
b0xxxxxx 4
b0xxxxxxx 4
bx 4
x*
x)
x(
x'
x&
x%
x$
x#
#80
0!
0+
#90
1!
1+
bx 5
bx0 4
bx00 4
bx000 4
bx0000 4
bx00000 4
bx000000 4
bx0000000 4
b0 4
0*
0)
0(
0'
0&
0%
0$
0#
#100
0!
0+
#110
1!
1+
b0 5
b0x 4
b0xx 4
b0xxx 4
b0xxxx 4
b0xxxxx 4
b0xxxxxx 4
b0xxxxxxx 4
bx 4
x*
x)
x(
x'
x&
x%
x$
x#
#120
0!
0+
#130
1!
1+
bx 5
bx0 4
bx00 4
bx000 4
bx0000 4
bx00000 4
bx000000 4
bx0000000 4
b0 4
0*
0)
0(
0'
0&
0%
0$
0#
#140
0!
0+
#150
1!
1+
b0 5
b0x 4
b0xx 4
b0xxx 4
b0xxxx 4
b0xxxxx 4
b0xxxxxx 4
b0xxxxxxx 4
bx 4
x*
x)
x(
x'
x&
x%
x$
x#
#160
0!
0+
#170
1!
1+
bx 5
bx0 4
bx00 4
bx000 4
bx0000 4
bx00000 4
bx000000 4
bx0000000 4
b0 4
0*
0)
0(
0'
0&
0%
0$
0#
#180
0!
0+
#190
1!
1+
b0 5
b0x 4
b0xx 4
b0xxx 4
b0xxxx 4
b0xxxxx 4
b0xxxxxx 4
b0xxxxxxx 4
bx 4
x*
x)
x(
x'
x&
x%
x$
x#
#200
b111000 "
0!
10
1/
1.
0+
b111000 5
#210
1!
1+
bx 5
bx0 4
bx10 4
bx010 4
bx0010 4
bx10010 4
bx010010 4
bx0010010 4
b10010010 4
0*
1)
0(
0'
1&
0%
0$
1#
#220
0!
0+
#230
1!
1+
b10010010 5
b1001001x 4
b100100xx 4
b10010xxx 4
b1001xxxx 4
b100xxxxx 4
b10xxxxxx 4
b1xxxxxxx 4
bx 4
x*
x)
x(
x'
x&
x%
x$
x#
#240
0!
0+
#250
1!
1+
bx 5
bx0 4
bx00 4
bx100 4
bx1100 4
bx11100 4
bx011100 4
bx0011100 4
b11100 4
0*
0)
1(
1'
1&
0%
0$
0#
#260
0!
0+
#270
1!
1+
b11100 5
b1110x 4
b111xx 4
b11xxx 4
b1xxxx 4
b0xxxxx 4
b0xxxxxx 4
b0xxxxxxx 4
bx 4
x*
x)
x(
x'
x&
x%
x$
x#
#280
0!
0+
#290
1!
1+
bx 5
bx0 4
bx10 4
bx010 4
bx0010 4
bx10010 4
bx110010 4
bx0110010 4
b10110010 4
0*
1)
0(
0'
1&
1%
0$
1#
#300
0!
0+
#310
1!
1+
b10110010 5
b1011001x 4
b101100xx 4
b10110xxx 4
b1011xxxx 4
b101xxxxx 4
b10xxxxxx 4
b1xxxxxxx 4
bx 4
x*
x)
x(
x'
x&
x%
x$
x#
#320
0!
0+
#330
1!
1+
bx 5
bx0 4
bx00 4
bx100 4
bx1100 4
bx11100 4
bx011100 4
bx0011100 4
b11100 4
0*
0)
1(
1'
1&
0%
0$
0#
#340
0!
0+
#350
1!
1+
b11100 5
b1110x 4
b111xx 4
b11xxx 4
b1xxxx 4
b0xxxxx 4
b0xxxxxx 4
b0xxxxxxx 4
bx 4
x*
x)
x(
x'
x&
x%
x$
x#
#360
0!
0+
#370
1!
1+
bx 5
bx0 4
bx10 4
bx010 4
bx0010 4
bx10010 4
bx110010 4
bx0110010 4
b10110010 4
0*
1)
0(
0'
1&
1%
0$
1#
#380
0!
0+
#390
1!
1+
b10110010 5
b1011001x 4
b101100xx 4
b10110xxx 4
b1011xxxx 4
b101xxxxx 4
b10xxxxxx 4
b1xxxxxxx 4
bx 4
x*
x)
x(
x'
x&
x%
x$
x#
#400
b1100011 "
0!
13
12
00
0/
1-
0+
b1100011 5
#410
1!
1+
bx 5
bx1 4
bx11 4
bx011 4
bx0011 4
bx10011 4
bx010011 4
bx1010011 4
b1010011 4
1*
1)
0(
0'
1&
0%
1$
0#
#420
0!
0+
#430
1!
1+
b1010011 5
b101001x 4
b10100xx 4
b1010xxx 4
b101xxxx 4
b10xxxxx 4
b1xxxxxx 4
b0xxxxxxx 4
bx 4
x*
x)
x(
x'
x&
x%
x$
x#
#440
0!
0+
#450
1!
1+
bx 5
bx1 4
bx11 4
bx011 4
bx0011 4
bx10011 4
bx010011 4
bx1010011 4
b1010011 4
1*
1)
0(
0'
1&
0%
1$
0#
#460
0!
0+
#470
1!
1+
b1010011 5
b101001x 4
b10100xx 4
b1010xxx 4
b101xxxx 4
b10xxxxx 4
b1xxxxxx 4
b0xxxxxxx 4
bx 4
x*
x)
x(
x'
x&
x%
x$
x#
#480
0!
0+
#490
1!
1+
bx 5
bx1 4
bx11 4
bx011 4
bx0011 4
bx10011 4
bx010011 4
bx1010011 4
b1010011 4
1*
1)
0(
0'
1&
0%
1$
0#
#500
0!
0+
#510
1!
1+
b1010011 5
b101001x 4
b10100xx 4
b1010xxx 4
b101xxxx 4
b10xxxxx 4
b1xxxxxx 4
b0xxxxxxx 4
bx 4
x*
x)
x(
x'
x&
x%
x$
x#
#520
0!
0+
#530
1!
1+
bx 5
bx1 4
bx11 4
bx011 4
bx0011 4
bx10011 4
bx010011 4
bx1010011 4
b1010011 4
1*
1)
0(
0'
1&
0%
1$
0#
#540
0!
0+
#550
1!
1+
b1010011 5
b101001x 4
b10100xx 4
b1010xxx 4
b101xxxx 4
b10xxxxx 4
b1xxxxxx 4
b0xxxxxxx 4
bx 4
x*
x)
x(
x'
x&
x%
x$
x#
#560
0!
0+
#570
1!
1+
bx 5
bx1 4
bx11 4
bx011 4
bx0011 4
bx10011 4
bx010011 4
bx1010011 4
b1010011 4
1*
1)
0(
0'
1&
0%
1$
0#
#580
0!
0+
#590
1!
1+
b1010011 5
b101001x 4
b10100xx 4
b1010xxx 4
b101xxxx 4
b10xxxxx 4
b1xxxxxx 4
b0xxxxxxx 4
bx 4
x*
x)
x(
x'
x&
x%
x$
x#
#600
b1111100 "
0!
03
02
11
10
1/
0+
b1111100 5
#610
1!
1+
bx 5
bx0 4
bx10 4
bx010 4
bx0010 4
bx10010 4
bx110010 4
bx0110010 4
b10110010 4
0*
1)
0(
0'
1&
1%
0$
1#
#620
0!
0+
#630
1!
1+
b10110010 5
b1011001x 4
b101100xx 4
b10110xxx 4
b1011xxxx 4
b101xxxxx 4
b10xxxxxx 4
b1xxxxxxx 4
bx 4
x*
x)
x(
x'
x&
x%
x$
x#
#640
0!
0+
#650
1!
1+
bx 5
bx0 4
bx00 4
bx100 4
bx1100 4
bx11100 4
bx011100 4
bx0011100 4
b11100 4
0*
0)
1(
1'
1&
0%
0$
0#
#660
0!
0+
#670
1!
1+
b11100 5
b1110x 4
b111xx 4
b11xxx 4
b1xxxx 4
b0xxxxx 4
b0xxxxxx 4
b0xxxxxxx 4
bx 4
x*
x)
x(
x'
x&
x%
x$
x#
#680
0!
0+
#690
1!
1+
bx 5
bx0 4
bx10 4
bx010 4
bx0010 4
bx10010 4
bx110010 4
bx0110010 4
b10110010 4
0*
1)
0(
0'
1&
1%
0$
1#
#700
0!
0+
#710
1!
1+
b10110010 5
b1011001x 4
b101100xx 4
b10110xxx 4
b1011xxxx 4
b101xxxxx 4
b10xxxxxx 4
b1xxxxxxx 4
bx 4
x*
x)
x(
x'
x&
x%
x$
x#
#720
0!
0+
#730
1!
1+
bx 5
bx0 4
bx00 4
bx100 4
bx1100 4
bx11100 4
bx011100 4
bx0011100 4
b11100 4
0*
0)
1(
1'
1&
0%
0$
0#
#740
0!
0+
#750
1!
1+
b11100 5
b1110x 4
b111xx 4
b11xxx 4
b1xxxx 4
b0xxxxx 4
b0xxxxxx 4
b0xxxxxxx 4
bx 4
x*
x)
x(
x'
x&
x%
x$
x#
#760
0!
0+
#770
1!
1+
bx 5
bx0 4
bx10 4
bx010 4
bx0010 4
bx10010 4
bx110010 4
bx0110010 4
b10110010 4
0*
1)
0(
0'
1&
1%
0$
1#
#780
0!
0+
#790
1!
1+
b10110010 5
b1011001x 4
b101100xx 4
b10110xxx 4
b1011xxxx 4
b101xxxxx 4
b10xxxxxx 4
b1xxxxxxx 4
bx 4
x*
x)
x(
x'
x&
x%
x$
x#
#800
b11111111 "
0!
13
12
1,
0+
b11111111 5
#810
1!
1+
bx 5
bx0 4
bx00 4
bx100 4
bx0100 4
bx10100 4
bx010100 4
bx0010100 4
b10100 4
0*
0)
1(
0'
1&
0%
0$
0#
#820
0!
0+
#830
1!
1+
b10100 5
b1010x 4
b101xx 4
b10xxx 4
b1xxxx 4
b0xxxxx 4
b0xxxxxx 4
b0xxxxxxx 4
bx 4
x*
x)
x(
x'
x&
x%
x$
x#
#840
0!
0+
#850
1!
1+
bx 5
bx0 4
bx10 4
bx010 4
bx0010 4
bx00010 4
bx100010 4
bx0100010 4
b100010 4
0*
1)
0(
0'
0&
1%
0$
0#
#860
0!
0+
#870
1!
1+
b100010 5
b10001x 4
b1000xx 4
b100xxx 4
b10xxxx 4
b1xxxxx 4
b0xxxxxx 4
b0xxxxxxx 4
bx 4
x*
x)
x(
x'
x&
x%
x$
x#
#880
0!
0+
#890
1!
1+
bx 5
bx0 4
bx10 4
bx010 4
bx1010 4
bx11010 4
bx011010 4
bx1011010 4
b1011010 4
0*
1)
0(
1'
1&
0%
1$
0#
#900
0!
0+
#910
1!
1+
b1011010 5
b101101x 4
b10110xx 4
b1011xxx 4
b101xxxx 4
b10xxxxx 4
b1xxxxxx 4
b0xxxxxxx 4
bx 4
x*
x)
x(
x'
x&
x%
x$
x#
#920
0!
0+
#930
1!
1+
bx 5
bx1 4
bx11 4
bx011 4
bx0011 4
bx10011 4
bx010011 4
bx1010011 4
b1010011 4
1*
1)
0(
0'
1&
0%
1$
0#
#940
0!
0+
#950
1!
1+
b1010011 5
b101001x 4
b10100xx 4
b1010xxx 4
b101xxxx 4
b10xxxxx 4
b1xxxxxx 4
b0xxxxxxx 4
bx 4
x*
x)
x(
x'
x&
x%
x$
x#
#960
0!
0+
#970
1!
1+
bx 5
bx1 4
bx11 4
bx011 4
bx0011 4
bx10011 4
bx010011 4
bx1010011 4
b1010011 4
1*
1)
0(
0'
1&
0%
1$
0#
#980
0!
0+
#990
1!
1+
b1010011 5
b101001x 4
b10100xx 4
b1010xxx 4
b101xxxx 4
b10xxxxx 4
b1xxxxxx 4
b0xxxxxxx 4
bx 4
x*
x)
x(
x'
x&
x%
x$
x#
