Gene_Network/init_val_gen.v
module init_val_gen (clk, current_val, fixed, cycle, init_val_out);
	input wire [3:0] clk;					//clock signal
	input wire [7:0] current_val;			//currnet init value of GENE NETWORK
	input wire fixed, cycle;				//flag of fixed point & cycle
	output reg [7:0] init_val_out;			//output init val++

	always @(negedge clk) begin					//synchronized with negative edge clock signal
		if (fixed || cycle)						//if fixed or cycle occured
			init_val_out = current_val + 1;		//init val++
	end
endmodule

Gene_Network/cycle.v
`timescale 1ns/100ps
module cycle (clk, init_val_chk, x, cycle_chk);
	input wire clk;
	input wire init_val_chk;
	input wire [7:0] x;
	output reg cycle_chk;
	reg [7:0] state_1;
	reg [7:0] state_2;

	always @(init_val_chk) begin
		flag = 0;
		state_1 = 8'b0000_0000;
		state_2 = 8'b0000_0000;
	end

	always @(posedge clk) begin
		if (state_2 == x)
			flag = 1;
		else
			flag = 0;
		state_2 = state_1;
		state_1 = x;
	end
endmodule

2023-1_논리회로/Gene_Network/fixed_point_checker.v
`timescale 1ns/100ps
module fixed_point_cheker(clk, rst, x, flag);
	input wire clk;						//clock signal
	input wire [7:0] rst;		//is init val changed?
	input wire [7:0] x;					//current gene state
	output reg flag;					//Fixed point has been FOUND!
	reg [7:0] state;					//state of x[t]

	always @(rst) begin		//if init val changed
		flag = 0;						//reset cycle  flag
	end

	always @(posedge clk) begin		//synchronized with positive edge clock signal
		if (state == x)	begin			//when x[t-1] == x[t+1]
			flag = 1;					//FIXED POINT!!!	
			$display("init: %d -> fixed_pnt: %b", rst, x);
		end else
			flag = 0;
		state = x;					//save x[t]
	end
endmodule

2023-1_논리회로/Gene_Network/gene_net.v
`timescale 1ns/100ps
module gene_net(clk, init_val_chk, x_out);
	input wire clk;					//clock signal
	input wire [7:0] init_val_chk;	//init value
	output reg [7:0] x_out;			//x[t+1]
	reg [7:0] state;				//x[t]
	reg [7:0] x;					//temporary value

	always @(init_val_chk)	begin	//if init val changed
		x_out = init_val_chk;		//set x[t] == init val
	end

	always @(posedge clk)	begin		//synchronized with positive edge clock signal
		state = x_out;
		x[0] = ~state[2] & state[6] & ~state[7];
		x[1] = (state[4] | state[5]) & ~state[7];
		x[2] = state[7];
		x[3] = state[1] & ~state[6];
		x[4] = state[1] | state[3];
		x[5] = state[2] & ~state[7];
		x[6] = state[1] & ~state[7];
		x[7] = ~(state[0] | state[1]) & (state[3] | state[6]);
		x_out = x;
	end

endmodule

Gene_Network/testbench.v
`timescale 1ns/100ps
`include "gene_net.v"
`include "fixed_point_checker.v"
`include "cycle.v"
`include "init_val_gen.v"

/*
gene_net TESTBENCH
	Give set of init value composed of making variable network state and verify module
*/
module tb_gene_net;
	/***gene_net INPUT***/
	reg clk;				//clock signal
	reg [7:0] init_val;		//init value of gene network
	/***gene_net OUTPUT***/
	wire [7:0] x;			//current state of gene network

	//clk signal generation
	initial begin
		clk = 0;
		forever #1 clk = ~clk;
	end

	//file dumping
	initial begin
		$dumpfile("wave.vcd");
		$dumpvars(0, tb_gene_net);
	end

	//input signal generation
	initial begin
		init_val = 8'b0000_0000;	//0 	fixed_point	-> 0000_0000
		#10
		init_val = 8'b0011_1000;	//56 	cycle occur	-> 0001_1100
		#10
		init_val = 8'b0110_0011;	//99 	fixed_point	-> 0101_0011
		#10
		init_val = 8'b0111_1100;	//124 	cycle occur	-> 1011_0010
		#10
		init_val = 8'b1111_1111;	//255 	fixed_point	-> 0101_0011
		#10
		$finish;					//end simulation
	end

	//instansiation gene_net
	gene_net GENE (.clk(clk), .init_val_chk(init_val), .x_out(x));

endmodule

/*
fixed_point_cheker TESTBENCH
	1. Input sets of init value that create various network states are entered into the module.
	2. Then again, input it's output to fixeg_point_checkr module.
*/
module tb_fixed_point_cheker;
	/***gene_net INPUT***/
	reg clk;							//clock signal
	reg [7:0] init_val;					//init value of gene network
	/***gene_net OUTPUT***/
	wire [7:0] x;						//current state of gene network
	/***fixed_point_checker OUTPUT***/
	wire fixed_chk;						//flag of fixed point checking
										//1: fixed point  0:none
	//clk signal generation
	initial begin
		clk = 0;
		forever #1 clk = ~clk;
	end

	initial begin
		init_val = 8'b0000_0000;	//0 	fixed_point	0000_0000
		#20
		init_val = 8'b0011_1000;	//56 	cycle		0001_1100
		#20
		init_val = 8'b0110_0011;	//99 	fixed_point	0101_0011
		#20
		init_val = 8'b0111_1100;	//124 	cycle		1011_0010
		#20
		init_val = 8'b1111_1111;	//255 	fixed_point	0101_0011
		#20
		$finish;					//end simulation
	end

	//instansiation gene_net
	fixed_point_cheker FIX	(.clk(clk), .rst(init_val), .x(x), .flag(fixed_chk));
	gene_net GENE			(.clk(clk), .init_val_chk(init_val), .x_out(x));

endmodule

/*
cycle TESTBENCH
	1. Input sets of init value that create various network states are entered into the module.
	2. Then again, input it's output to cycle module.
*/
module tb_cycle;
	/***gene_net INPUT***/
	reg clk;							//clock signal
	reg [7:0] init_val;					//init value of gene network
	/***gene_net OUTPUT***/
	wire [7:0] x;						//current state of gene network
	/***cycle OUTPUT***/
	wire cycle_chk;						//flag of cycle checking
										//1: cycle  0:none
	//clk signal generation
	initial begin
		clk = 0;
		forever #1 clk = ~clk;
	end

	initial begin
			init_val = 8'b0000_0000;	//0 	fixed_point	0000_0000
			#20
			init_val = 8'b0011_1000;	//56 	cycle		0001_1100
			#20
			init_val = 8'b0110_0011;	//99 	fixed_point	0101_0011
			#20
			init_val = 8'b0111_1100;	//124 	cycle		1011_0010
			#20
			init_val = 8'b1111_1111;	//255 	fixed_point	0101_0011
			#20
			$finish;					//end simulation
		end

	//instansiation gene_net
	cycle CYCLE		(.clk(clk), .rst(init_val), .x(x), .flag(cycle_chk));
	gene_net GENE	(.clk(clk), .init_val_chk(init_val), .x_out(x));

endmodule

2023-1_논리회로/Gene_Network/wave.vcd
$date
	Tue May 30 22:14:18 2023
$end
$version
	ModelSim Version 2020.1
$end
$timescale
	100ps
$end

$scope module tb_gene_net $end
$var reg 1 ! clk $end
$var reg 8 " init_val [7:0] $end
$var wire 1 # x [7] $end
$var wire 1 $ x [6] $end
$var wire 1 % x [5] $end
$var wire 1 & x [4] $end
$var wire 1 ' x [3] $end
$var wire 1 ( x [2] $end
$var wire 1 ) x [1] $end
$var wire 1 * x [0] $end

$scope module GENE $end
$var wire 1 + clk $end
$var wire 1 , init_val_chk [7] $end
$var wire 1 - init_val_chk [6] $end
$var wire 1 . init_val_chk [5] $end
$var wire 1 / init_val_chk [4] $end
$var wire 1 0 init_val_chk [3] $end
$var wire 1 1 init_val_chk [2] $end
$var wire 1 2 init_val_chk [1] $end
$var wire 1 3 init_val_chk [0] $end
$var reg 8 4 x_out [7:0] $end
$var reg 8 5 state [7:0] $end
$var reg 8 6 x [7:0] $end
$upscope $end
$upscope $end
$enddefinitions $end
#0
$dumpvars
0!
b0 "
b0 4
bx 5
bx 6
0*
0)
0(
0'
0&
0%
0$
0#
03
02
01
00
0/
0.
0-
0,
0+
$end
#10
1!
1+
b0 5
bx0 6
bx00 6
bx000 6
bx0000 6
bx00000 6
bx000000 6
bx0000000 6
b0 6
#20
0!
0+
#30
1!
1+
#40
0!
0+
#50
1!
1+
#60
0!
0+
#70
1!
1+
#80
0!
0+
#90
1!
1+
#100
b111000 "
0!
10
1/
1.
0+
b111000 4
1'
1&
1%
#110
1!
1+
b111000 5
b10 6
b10010 6
b10010010 6
b10010010 4
1)
0'
0%
1#
#120
0!
0+
#130
1!
1+
b10010010 5
b10010000 6
b10010100 6
b10011100 6
b11100 6
b11100 4
0)
1(
1'
0#
#140
0!
0+
#150
1!
1+
b11100 5
b11110 6
b11010 6
b10010 6
b110010 6
b10110010 6
b10110010 4
1)
0(
0'
1%
1#
#160
0!
0+
#170
1!
1+
b10110010 5
b10110000 6
b10110100 6
b10111100 6
b10011100 6
b11100 6
b11100 4
0)
1(
1'
0%
0#
#180
0!
0+
#190
1!
1+
b11100 5
b11110 6
b11010 6
b10010 6
b110010 6
b10110010 6
b10110010 4
1)
0(
0'
1%
1#
#200
b1100011 "
0!
13
12
00
0/
1-
0+
b1100011 4
1*
0&
1$
0#
#210
1!
1+
b1100011 5
b10110011 6
b10010011 6
b11010011 6
b1010011 6
b1010011 4
1&
0%
#220
0!
0+
#230
1!
1+
b1010011 5
#240
0!
0+
#250
1!
1+
#260
0!
0+
#270
1!
1+
#280
0!
0+
#290
1!
1+
#300
b1111100 "
0!
03
02
11
10
1/
0+
b1111100 4
0*
0)
1(
1'
1%
#310
1!
1+
b1111100 5
b1010010 6
b1110010 6
b110010 6
b10110010 6
b10110010 4
1)
0(
0'
0$
1#
#320
0!
0+
#330
1!
1+
b10110010 5
b10110000 6
b10110100 6
b10111100 6
b10011100 6
b11100 6
b11100 4
0)
1(
1'
0%
0#
#340
0!
0+
#350
1!
1+
b11100 5
b11110 6
b11010 6
b10010 6
b110010 6
b10110010 6
b10110010 4
1)
0(
0'
1%
1#
#360
0!
0+
#370
1!
1+
b10110010 5
b10110000 6
b10110100 6
b10111100 6
b10011100 6
b11100 6
b11100 4
0)
1(
1'
0%
0#
#380
0!
0+
#390
1!
1+
b11100 5
b11110 6
b11010 6
b10010 6
b110010 6
b10110010 6
b10110010 4
1)
0(
0'
1%
1#
#400
b11111111 "
0!
13
12
1,
0+
b11111111 4
1*
1(
1'
1$
#410
1!
1+
b11111111 5
b10110000 6
b10110100 6
b10010100 6
b10100 6
b10100 4
0*
0)
0'
0%
0$
0#
#420
0!
0+
#430
1!
1+
b10100 5
b10110 6
b10010 6
b10 6
b100010 6
b100010 4
1)
0(
0&
1%
#440
0!
0+
#450
1!
1+
b100010 5
b101010 6
b111010 6
b11010 6
b1011010 6
b1011010 4
1'
1&
0%
1$
#460
0!
0+
#470
1!
1+
b1011010 5
b1011011 6
b1010011 6
b1010011 4
1*
0'
#480
0!
0+
#490
1!
1+
b1010011 5
